py_hasura/__init__.py
py_hasura/flatten_dict.py
py_hasura/gql_client.py
py_hasura/hasura_client.py
pyhasura/__init__.py
pyhasura/dbml_hasura.py
pyhasura/flatten_dict.py
pyhasura/gql_client.py
pyhasura/hasura_client.py
pyhasura/helpers.py
pyhasura/keys.py
pyhasura/relationships.py
pyhasura/synonyms.py
pyhasura/upload_csvs.py
pyhasura/vectorize.py
pyhasura-1.0.36.dist-info/LICENSE
pyhasura-1.0.36.dist-info/METADATA
pyhasura-1.0.36.dist-info/WHEEL
pyhasura-1.0.36.dist-info/top_level.txt
pyhasura-1.0.36.dist-info/RECORD
