Metadata-Version: 2.1
Name: pyhasura
Version: 1.0.36
Summary: A Python library to simplify Hasura, GraphQL and Machine Learning
Author-email: Kenneth Stott <ken@kenstott.com>
Project-URL: repository, https://github.com/kenstott/pyhasura
Keywords: graphql,hasura,ml,ai,machine learning,arrow
Requires-Python: >=3.8
License-File: LICENSE
Requires-Dist: python-dotenv
Requires-Dist: gql
Requires-Dist: pandas
Requires-Dist: pyarrow
Requires-Dist: scikit-learn
Requires-Dist: setuptools
Requires-Dist: aiohttp
Requires-Dist: pymongo
Requires-Dist: python-dateutil
Requires-Dist: scipy
Requires-Dist: gensim
Requires-Dist: torch
Requires-Dist: transformers
Requires-Dist: requests
Requires-Dist: graphql-core
Requires-Dist: nltk
Requires-Dist: pluralizer
Requires-Dist: jsondiff
Requires-Dist: numpy
Requires-Dist: price-parser
Requires-Dist: chardet
Requires-Dist: SQLAlchemy
Requires-Dist: python-camelcaser
Requires-Dist: pydbml
Requires-Dist: neo4j
Requires-Dist: diskcache
Requires-Dist: sentence-transformers
Requires-Dist: requests-toolbelt
